ndvis/CSV_dlg.py
ndvis/NDVisualizer_GUI.py
ndvis/NDVisualizer_PySide6.py
ndvis/PlotWindow.py
ndvis/__init__.py
ndvis/__main__.py
ndvis/_version.py
ndvis/icon.ico
ndvis/utils.py
ndvis-0.2.5.dist-info/METADATA
ndvis-0.2.5.dist-info/WHEEL
ndvis-0.2.5.dist-info/licenses/LICENSE
ndvis-0.2.5.dist-info/RECORD
