Metadata-Version: 2.4
Name: ndvis
Version: 0.2.5
Summary: A Python package for N-Dimensional data visualization.
Project-URL: Homepage, https://github.com/yuanliu-repo/NDVisualizer_py
Project-URL: Repository, https://github.com/yuanliu-repo/NDVisualizer_py
Project-URL: Issues, https://github.com/yuanliu-repo/NDVisualizer_py/issues
Author-email: "Y. Liu" <lewisyuan@gmail.com>
License: GPL-3.0-or-later
License-File: LICENSE
Classifier: Operating System :: OS Independent
Classifier: Programming Language :: Python :: 3
Requires-Dist: matplotlib==3.10.3
Requires-Dist: numpy==2.2.6
Requires-Dist: pandas==2.3.0
Requires-Dist: pymatreader==1.0.0
Requires-Dist: pyside6-essentials==6.9.0
Requires-Dist: pyside6==6.9.0
Requires-Dist: superqt==0.7.3
